py_advanced_search_list_prod/__init__.py
py_advanced_search_list_prod/function.py
py_advanced_search_list_prod-0.0.5.dist-info/LICENSE
py_advanced_search_list_prod-0.0.5.dist-info/METADATA
py_advanced_search_list_prod-0.0.5.dist-info/WHEEL
py_advanced_search_list_prod-0.0.5.dist-info/top_level.txt
py_advanced_search_list_prod-0.0.5.dist-info/RECORD
