Metadata-Version: 2.1
Name: py-advanced-search-list-prod
Version: 0.0.5
Summary: Package to advance search
Home-page: https://github.com/saurabhranem/python_library
Author: Saurabh
Author-email: saurabhrane.m@gmail.com
License: UNKNOWN
Platform: UNKNOWN
Classifier: Programming Language :: Python :: 3
Classifier: License :: OSI Approved :: MIT License
Classifier: Operating System :: OS Independent
Requires-Dist: fuzzywuzzy
Requires-Dist: fuzzywuzzy[speedup]
